pyti/__init__.py
pyti/accumulation_distribution.py
pyti/aroon.py
pyti/average_true_range.py
pyti/average_true_range_percent.py
pyti/bollinger_bands.py
pyti/catch_errors.py
pyti/chaikin_money_flow.py
pyti/chande_momentum_oscillator.py
pyti/commodity_channel_index.py
pyti/detrended_price_oscillator.py
pyti/directional_indicators.py
pyti/double_exponential_moving_average.py
pyti/double_smoothed_stochastic.py
pyti/exponential_moving_average.py
pyti/function_helper.py
pyti/hull_moving_average.py
pyti/ichimoku_cloud.py
pyti/keltner_bands.py
pyti/linear_weighted_moving_average.py
pyti/momentum.py
pyti/money_flow.py
pyti/money_flow_index.py
pyti/moving_average_convergence_divergence.py
pyti/moving_average_envelope.py
pyti/on_balance_volume.py
pyti/price_channels.py
pyti/price_oscillator.py
pyti/rate_of_change.py
pyti/relative_strength_index.py
pyti/simple_moving_average.py
pyti/smoothed_moving_average.py
pyti/standard_deviation.py
pyti/standard_variance.py
pyti/stochastic.py
pyti/stochrsi.py
pyti/triangular_moving_average.py
pyti/triple_exponential_moving_average.py
pyti/true_range.py
pyti/typical_price.py
pyti/ultimate_oscillator.py
pyti/vertical_horizontal_filter.py
pyti/volatility.py
pyti/volume_adjusted_moving_average.py
pyti/volume_index.py
pyti/volume_oscillator.py
pyti/weighted_moving_average.py
pyti/williams_percent_r.py
pyti-0.2.2.dist-info/DESCRIPTION.rst
pyti-0.2.2.dist-info/METADATA
pyti-0.2.2.dist-info/RECORD
pyti-0.2.2.dist-info/WHEEL
pyti-0.2.2.dist-info/metadata.json
pyti-0.2.2.dist-info/top_level.txt
